{"image_url": "https://s3-media2.fl.yelpcdn.com/bphoto/1lXoWpV4ngOQVQqLb8h9Eg/o.jpg", "hours": [{"hours_type": "REGULAR", "is_open_now": false, "open": [{"start": "1100", "day": 0, "end": "1500", "is_overnight": false}, {"start": "1700", "day": 0, "end": "2000", "is_overnight": false}, {"start": "1100", "day": 1, "end": "1500", "is_overnight": false}, {"start": "1700", "day": 1, "end": "2000", "is_overnight": false}, {"start": "1100", "day": 2, "end": "1500", "is_overnight": false}, {"start": "1700", "day": 2, "end": "2000", "is_overnight": false}, {"start": "1100", "day": 3, "end": "1500", "is_overnight": false}, {"start": "1700", "day": 3, "end": "2000", "is_overnight": false}, {"start": "1100", "day": 4, "end": "1500", "is_overnight": false}, {"start": "1700", "day": 4, "end": "2000", "is_overnight": false}, {"start": "1300", "day": 5, "end": "1500", "is_overnight": false}, {"start": "1700", "day": 5, "end": "2000", "is_overnight": false}]}], "photos": ["https://s3-media1.fl.yelpcdn.com/bphoto/1lXoWpV4ngOQVQqLb8h9Eg/o.jpg", "https://s3-media2.fl.yelpcdn.com/bphoto/TK90VXZJhbiQSiyTwk8i3A/o.jpg", "https://s3-media3.fl.yelpcdn.com/bphoto/4tpZE_pyvufF0mbzOEGlVg/o.jpg"], "phone": "+12064675046", "term": "restaurants", "coordinates": {"latitude": 47.6097914, "longitude": -122.32556}, "price": "$", "is_closed": false, "categories": [{"alias": "mediterranean", "title": "Mediterranean"}, {"alias": "lebanese", "title": "Lebanese"}], "url": "https://www.yelp.com/biz/mediterranean-kitchen-kabob-house-seattle?adjust_creative=92p07_JjKyriZTQxAXRiKQ&utm_campaign=yelp_api_v3&utm_medium=api_v3_business_lookup&utm_source=92p07_JjKyriZTQxAXRiKQ", "review_count": 143, "is_claimed": true, "name": "Mediterranean Kitchen Kabob House", "id": "mediterranean-kitchen-kabob-house-seattle", "rating": 4.0, "location": {"address3": "", "address1": "1009 Boren Ave", "state": "WA", "country": "US", "address2": "", "zip_code": "98104", "city": "Seattle"}}