{"image_url": "https://s3-media3.fl.yelpcdn.com/bphoto/GZR_j1R-ZVubOwZiHrmvLQ/o.jpg", "hours": [{"hours_type": "REGULAR", "is_open_now": false, "open": [{"start": "1000", "day": 0, "end": "2200", "is_overnight": false}, {"start": "1000", "day": 1, "end": "2200", "is_overnight": false}, {"start": "1000", "day": 2, "end": "2200", "is_overnight": false}, {"start": "1000", "day": 3, "end": "2200", "is_overnight": false}, {"start": "1000", "day": 4, "end": "0000", "is_overnight": false}, {"start": "1000", "day": 5, "end": "0000", "is_overnight": false}, {"start": "1000", "day": 6, "end": "2200", "is_overnight": false}]}], "photos": ["https://s3-media3.fl.yelpcdn.com/bphoto/GZR_j1R-ZVubOwZiHrmvLQ/o.jpg", "https://s3-media3.fl.yelpcdn.com/bphoto/umrJ4G8hh2qLzOSAaLH_yg/o.jpg", "https://s3-media2.fl.yelpcdn.com/bphoto/YHHui-Lsa6Yjjj1FQ4HJIA/o.jpg"], "phone": "+12068601404", "term": "restaurants", "coordinates": {"latitude": 47.5998406645559, "longitude": -122.317832050262}, "price": "$$", "is_closed": false, "categories": [{"alias": "vietnamese", "title": "Vietnamese"}, {"alias": "noodles", "title": "Noodles"}], "url": "https://www.yelp.com/biz/tamarind-tree-seattle?adjust_creative=92p07_JjKyriZTQxAXRiKQ&utm_campaign=yelp_api_v3&utm_medium=api_v3_business_lookup&utm_source=92p07_JjKyriZTQxAXRiKQ", "review_count": 1043, "is_claimed": true, "name": "Tamarind Tree", "id": "tamarind-tree-seattle", "rating": 4.0, "location": {"address3": "", "address1": "1036 S Jackson St", "state": "WA", "country": "US", "address2": "Ste A", "zip_code": "98104", "city": "Seattle"}}