{"image_url": "https://s3-media1.fl.yelpcdn.com/bphoto/ZtoCZxcPipu9k1_vI5silA/o.jpg", "hours": [{"hours_type": "REGULAR", "is_open_now": true, "open": [{"start": "1200", "day": 1, "end": "1430", "is_overnight": false}, {"start": "1800", "day": 1, "end": "1100", "is_overnight": true}, {"start": "1200", "day": 2, "end": "1430", "is_overnight": false}, {"start": "1800", "day": 2, "end": "1100", "is_overnight": true}, {"start": "1200", "day": 3, "end": "1430", "is_overnight": false}, {"start": "1800", "day": 3, "end": "1100", "is_overnight": true}, {"start": "1200", "day": 4, "end": "1430", "is_overnight": false}, {"start": "1800", "day": 4, "end": "1100", "is_overnight": true}, {"start": "1200", "day": 5, "end": "1430", "is_overnight": false}, {"start": "1800", "day": 5, "end": "1100", "is_overnight": true}, {"start": "1200", "day": 6, "end": "1430", "is_overnight": false}, {"start": "1800", "day": 6, "end": "2130", "is_overnight": false}]}], "photos": ["https://s3-media2.fl.yelpcdn.com/bphoto/ZtoCZxcPipu9k1_vI5silA/o.jpg", "https://s3-media1.fl.yelpcdn.com/bphoto/R9Z9uykY9jecq08XfEVkrA/o.jpg", "https://s3-media4.fl.yelpcdn.com/bphoto/3YawXGWrPJFbYBOh2fuHbA/o.jpg"], "phone": "+61283888688", "term": "restaurants", "coordinates": {"latitude": -33.8860163, "longitude": 151.2399132}, "price": "$$$", "is_closed": false, "categories": [{"alias": "modern_australian", "title": "Modern Australian"}, {"alias": "bistros", "title": "Bistros"}], "url": "https://www.yelp.com/biz/chiswick-woollahra-2?adjust_creative=92p07_JjKyriZTQxAXRiKQ&utm_campaign=yelp_api_v3&utm_medium=api_v3_business_lookup&utm_source=92p07_JjKyriZTQxAXRiKQ", "review_count": 43, "is_claimed": true, "name": "Chiswick", "id": "chiswick-woollahra-2", "rating": 4.0, "location": {"address3": "", "state": "NSW", "address1": "65 Ocean St", "country": "AU", "address2": "", "zip_code": "2025", "city": "Woollahra"}}