{"image_url": "https://s3-media2.fl.yelpcdn.com/bphoto/RxmBTp8UVu7U5GrU482aww/o.jpg", "hours": [{"hours_type": "REGULAR", "is_open_now": false, "open": [{"start": "1100", "day": 1, "end": "2130", "is_overnight": false}, {"start": "1100", "day": 2, "end": "2130", "is_overnight": false}, {"start": "1100", "day": 3, "end": "2130", "is_overnight": false}, {"start": "1100", "day": 4, "end": "2200", "is_overnight": false}, {"start": "1100", "day": 5, "end": "2200", "is_overnight": false}, {"start": "1200", "day": 6, "end": "2130", "is_overnight": false}]}], "photos": ["https://s3-media2.fl.yelpcdn.com/bphoto/RxmBTp8UVu7U5GrU482aww/o.jpg", "https://s3-media3.fl.yelpcdn.com/bphoto/vmUVx3jdSgmNyz1vIFgO1A/o.jpg", "https://s3-media4.fl.yelpcdn.com/bphoto/cD_gzHZr0sJwlytZw66xMA/o.jpg"], "phone": "+17136647686", "term": "restaurants", "coordinates": {"latitude": 29.68877, "longitude": -95.4131533}, "price": "$$", "is_closed": false, "categories": [{"alias": "sushi", "title": "Sushi Bars"}, {"alias": "japanese", "title": "Japanese"}], "url": "https://www.yelp.com/biz/asahi-sushi-houston?adjust_creative=92p07_JjKyriZTQxAXRiKQ&utm_campaign=yelp_api_v3&utm_medium=api_v3_business_lookup&utm_source=92p07_JjKyriZTQxAXRiKQ", "review_count": 217, "is_claimed": true, "name": "Asahi Sushi", "id": "asahi-sushi-houston", "rating": 4.0, "location": {"address3": "", "address1": "8236 Kirby Dr", "state": "TX", "country": "US", "address2": "Ste 200", "zip_code": "77054", "city": "Houston"}}