{"image_url": "https://s3-media3.fl.yelpcdn.com/bphoto/jofoXoPW7NB_5Q1A8r5kaQ/o.jpg", "hours": [{"hours_type": "REGULAR", "is_open_now": false, "open": [{"start": "1100", "day": 1, "end": "2200", "is_overnight": false}, {"start": "1100", "day": 2, "end": "2200", "is_overnight": false}, {"start": "1100", "day": 3, "end": "2200", "is_overnight": false}, {"start": "1100", "day": 4, "end": "2300", "is_overnight": false}, {"start": "1100", "day": 5, "end": "2300", "is_overnight": false}, {"start": "1100", "day": 6, "end": "2200", "is_overnight": false}]}], "photos": ["https://s3-media2.fl.yelpcdn.com/bphoto/jofoXoPW7NB_5Q1A8r5kaQ/o.jpg", "https://s3-media2.fl.yelpcdn.com/bphoto/u8kn0fZTtmSNwxgZm7nhsw/o.jpg", "https://s3-media2.fl.yelpcdn.com/bphoto/jy5_6-lK_qAam5USyniJ7w/o.jpg"], "phone": "+17045319525", "term": "restaurants", "coordinates": {"latitude": 35.23666, "longitude": -80.77453}, "price": "$$", "is_closed": false, "categories": [{"alias": "vietnamese", "title": "Vietnamese"}], "url": "https://www.yelp.com/biz/lang-van-vietnamese-charlotte?adjust_creative=92p07_JjKyriZTQxAXRiKQ&utm_campaign=yelp_api_v3&utm_medium=api_v3_business_lookup&utm_source=92p07_JjKyriZTQxAXRiKQ", "review_count": 240, "is_claimed": false, "name": "Lang Van Vietnamese", "id": "lang-van-vietnamese-charlotte", "rating": 4.0, "location": {"address3": "", "state": "NC", "address1": "3019 Shamrock Dr", "country": "US", "address2": "", "zip_code": "28215", "city": "Charlotte"}}