{"image_url": "https://s3-media2.fl.yelpcdn.com/bphoto/IZZfKHGaYw3CS_Lg-nGgbQ/o.jpg", "hours": [{"hours_type": "REGULAR", "is_open_now": false, "open": [{"start": "1200", "day": 2, "end": "2300", "is_overnight": false}, {"start": "1200", "day": 3, "end": "2300", "is_overnight": false}, {"start": "1200", "day": 4, "end": "2300", "is_overnight": false}, {"start": "1200", "day": 5, "end": "2300", "is_overnight": false}]}], "id": "buffalo-dining-club-darlinghurst", "phone": "+61293324052", "term": "restaurants", "rating": 4.5, "price": "$$", "is_closed": false, "categories": [{"alias": "italian", "title": "Italian"}], "url": "https://www.yelp.com/biz/buffalo-dining-club-darlinghurst?adjust_creative=92p07_JjKyriZTQxAXRiKQ&utm_campaign=yelp_api_v3&utm_medium=api_v3_business_lookup&utm_source=92p07_JjKyriZTQxAXRiKQ", "review_count": 41, "is_claimed": false, "name": "Buffalo Dining Club", "photos": ["https://s3-media4.fl.yelpcdn.com/bphoto/IZZfKHGaYw3CS_Lg-nGgbQ/o.jpg", "https://s3-media3.fl.yelpcdn.com/bphoto/331nH34Y3HdLfBAXAMKESw/o.jpg", "https://s3-media2.fl.yelpcdn.com/bphoto/4aggiETwgmjhvOLnmQO8Ig/o.jpg"], "coordinates": {"latitude": -33.877555, "longitude": 151.221935}, "location": {"address3": "", "state": "NSW", "address1": "116 Surrey St", "country": "AU", "address2": "", "zip_code": "2010", "city": "Darlinghurst"}}