{"image_url": "https://s3-media2.fl.yelpcdn.com/bphoto/zbEP8JULjn0r_rkVGCh7cQ/o.jpg", "hours": [{"hours_type": "REGULAR", "is_open_now": false, "open": [{"start": "1100", "day": 0, "end": "1600", "is_overnight": false}, {"start": "1100", "day": 1, "end": "1600", "is_overnight": false}, {"start": "1100", "day": 2, "end": "1600", "is_overnight": false}, {"start": "1100", "day": 3, "end": "1600", "is_overnight": false}, {"start": "1100", "day": 4, "end": "1600", "is_overnight": false}]}], "photos": ["https://s3-media3.fl.yelpcdn.com/bphoto/zbEP8JULjn0r_rkVGCh7cQ/o.jpg", "https://s3-media2.fl.yelpcdn.com/bphoto/EUauyfuJJkwmGdQqpZiDiQ/o.jpg", "https://s3-media2.fl.yelpcdn.com/bphoto/35u6xd783snFHxXHg6Qyjg/o.jpg"], "phone": "+13139620166", "term": "restaurants", "coordinates": {"latitude": 42.3355026, "longitude": -83.0466919}, "price": "$", "is_closed": false, "categories": [{"alias": "delis", "title": "Delis"}], "url": "https://www.yelp.com/biz/steves-detroit-deli-detroit?adjust_creative=92p07_JjKyriZTQxAXRiKQ&utm_campaign=yelp_api_v3&utm_medium=api_v3_business_lookup&utm_source=92p07_JjKyriZTQxAXRiKQ", "review_count": 18, "is_claimed": false, "name": "Steve's Detroit Deli", "id": "steves-detroit-deli-detroit", "rating": 4.5, "location": {"address3": "", "state": "MI", "address1": "212 E Grand River Ave", "country": "US", "address2": "", "zip_code": "48226", "city": "Detroit"}}