{"image_url": "https://s3-media1.fl.yelpcdn.com/bphoto/Cw0kh6AInRAoCp9ifn1XxA/o.jpg", "photos": ["https://s3-media2.fl.yelpcdn.com/bphoto/Cw0kh6AInRAoCp9ifn1XxA/o.jpg", "https://s3-media4.fl.yelpcdn.com/bphoto/N4xSVuomyQQNdIRoxjf22w/o.jpg", "https://s3-media1.fl.yelpcdn.com/bphoto/vH8KSBCRh_IM4xoAII0diA/o.jpg"], "phone": "", "term": "attractions", "rating": 4.5, "is_closed": false, "categories": [{"alias": "lakes", "title": "Lakes"}], "url": "https://www.yelp.com/biz/jacqueline-kennedy-onassis-reservoir-new-york?adjust_creative=92p07_JjKyriZTQxAXRiKQ&utm_campaign=yelp_api_v3&utm_medium=api_v3_business_lookup&utm_source=92p07_JjKyriZTQxAXRiKQ", "review_count": 76, "is_claimed": false, "name": "Jacqueline Kennedy Onassis Reservoir", "id": "jacqueline-kennedy-onassis-reservoir-new-york", "coordinates": {"latitude": 40.7862605212217, "longitude": -73.9620208740234}, "location": {"address3": "", "address1": "", "state": "NY", "country": "US", "address2": "", "zip_code": "10022", "city": "New York"}}