{"image_url": "", "photos": [], "phone": "+61262577231", "term": "hotels", "rating": 0.0, "is_closed": false, "categories": [{"alias": "travelservices", "title": "Travel Services"}], "url": "https://www.yelp.com/biz/canberra-walk-in-aviary-nicholls?adjust_creative=92p07_JjKyriZTQxAXRiKQ&utm_campaign=yelp_api_v3&utm_medium=api_v3_business_lookup&utm_source=92p07_JjKyriZTQxAXRiKQ", "review_count": 0, "is_claimed": false, "name": "Canberra Walk in Aviary", "id": "canberra-walk-in-aviary-nicholls", "coordinates": {"latitude": -35.1841812, "longitude": 149.0991669}, "location": {"address3": null, "state": "ACT", "address1": "Unit 13, Federation Square O\u00d4\u00c7\u00d6Hanlon Pl", "country": "AU", "address2": null, "zip_code": "2913", "city": "Nicholls"}}