{"image_url": "", "photos": [], "phone": "+61262438333", "term": "hotels", "rating": 0.0, "is_closed": false, "categories": [{"alias": "venues", "title": "Venues & Event Spaces"}, {"alias": "restaurants", "title": "Restaurants"}], "url": "https://www.yelp.com/biz/capital-executive-apartment-hotel-canberra-city-2?adjust_creative=92p07_JjKyriZTQxAXRiKQ&utm_campaign=yelp_api_v3&utm_medium=api_v3_business_lookup&utm_source=92p07_JjKyriZTQxAXRiKQ", "review_count": 0, "is_claimed": false, "name": "Capital Executive Apartment Hotel", "id": "capital-executive-apartment-hotel-canberra-city-2", "coordinates": {"latitude": -35.2694016, "longitude": 149.1399994}, "location": {"address3": null, "state": "ACT", "address1": "Girrahween St", "country": "AU", "address2": null, "zip_code": "2601", "city": "Canberra City"}}