{"image_url": "", "photos": [], "phone": "+17247258000", "term": "attractions", "rating": 1.0, "is_closed": false, "categories": [], "url": "https://www.yelp.com/biz/enet-technologies-friendswood?adjust_creative=92p07_JjKyriZTQxAXRiKQ&utm_campaign=yelp_api_v3&utm_medium=api_v3_business_lookup&utm_source=92p07_JjKyriZTQxAXRiKQ", "review_count": 1, "is_claimed": false, "name": "Enet Technologies", "id": "enet-technologies-friendswood", "coordinates": {"latitude": 29.5329094, "longitude": -95.2058868}, "location": {"address3": "", "state": "TX", "address1": "104 Peacan Drive", "country": "US", "address2": "", "zip_code": "77546", "city": "Friendswood"}}