{"image_url": "https://s3-media4.fl.yelpcdn.com/bphoto/Gf7zAzedIheglpnJLSt3Sw/o.jpg", "id": "mk2-quai-de-seine-paris", "phone": "+33140368572", "term": "attractions", "rating": 4.0, "price": "\u20ac\u20ac\u20ac", "is_closed": false, "categories": [{"alias": "movietheaters", "title": "Cinema"}], "url": "https://www.yelp.com/biz/mk2-quai-de-seine-paris?adjust_creative=92p07_JjKyriZTQxAXRiKQ&utm_campaign=yelp_api_v3&utm_medium=api_v3_business_lookup&utm_source=92p07_JjKyriZTQxAXRiKQ", "review_count": 41, "is_claimed": false, "name": "Mk2 Quai de Seine", "photos": ["https://s3-media1.fl.yelpcdn.com/bphoto/Gf7zAzedIheglpnJLSt3Sw/o.jpg", "https://s3-media4.fl.yelpcdn.com/bphoto/m5tL9njKOTWyLbdfa2TwOA/o.jpg", "https://s3-media4.fl.yelpcdn.com/bphoto/2XN4kvMBTFp221YNGkOotA/o.jpg"], "coordinates": {"latitude": 48.88533, "longitude": 2.3718093}, "location": {"address3": null, "city": "Paris", "state": "75", "address1": "14 quai de la Seine", "address2": null, "zip_code": "75019", "country": "FR"}}