{"image_url": "https://s3-media4.fl.yelpcdn.com/bphoto/1whMTFcjbL9XgojIfct96g/o.jpg", "id": "perfect-h\u00f4tel-et-hostel-paris-2", "phone": "+33142811886", "term": "attractions", "rating": 3.0, "price": "\u20ac", "is_closed": false, "categories": [{"alias": "hotels", "title": "Hotels"}, {"alias": "hostels", "title": "Hostels"}], "url": "https://www.yelp.com/biz/perfect-h%C3%B4tel-et-hostel-paris-2?adjust_creative=92p07_JjKyriZTQxAXRiKQ&utm_campaign=yelp_api_v3&utm_medium=api_v3_business_lookup&utm_source=92p07_JjKyriZTQxAXRiKQ", "review_count": 13, "is_claimed": false, "name": "Perfect H\u00f4tel & Hostel", "photos": ["https://s3-media2.fl.yelpcdn.com/bphoto/1whMTFcjbL9XgojIfct96g/o.jpg", "https://s3-media2.fl.yelpcdn.com/bphoto/Y2VZpqkfGNooQ7FDWoH0Vg/o.jpg", "https://s3-media2.fl.yelpcdn.com/bphoto/wv8XFoALVNjQFgFP7PXhuw/o.jpg"], "coordinates": {"latitude": 48.87985, "longitude": 2.34348}, "location": {"address3": "", "city": "Paris", "state": "75", "address1": "39 rue Rodier", "address2": "", "zip_code": "75009", "country": "FR"}}