{"image_url": "https://s3-media2.fl.yelpcdn.com/bphoto/IT7xg4DuE7Z8LIwlxbUYbQ/o.jpg", "hours": [{"hours_type": "REGULAR", "is_open_now": true, "open": [{"start": "0630", "day": 3, "end": "2300", "is_overnight": false}, {"start": "1830", "day": 4, "end": "0000", "is_overnight": false}, {"start": "1830", "day": 5, "end": "0000", "is_overnight": false}, {"start": "1830", "day": 6, "end": "2300", "is_overnight": false}]}], "id": "goblyns-glen-los-gatos", "phone": "+14086056162", "term": "attractions", "rating": 3.0, "is_closed": false, "categories": [{"alias": "festivals", "title": "Festivals"}], "url": "https://www.yelp.com/biz/goblyns-glen-los-gatos?adjust_creative=92p07_JjKyriZTQxAXRiKQ&utm_campaign=yelp_api_v3&utm_medium=api_v3_business_lookup&utm_source=92p07_JjKyriZTQxAXRiKQ", "review_count": 18, "is_claimed": false, "name": "Goblyns Glen", "photos": ["https://s3-media3.fl.yelpcdn.com/bphoto/IT7xg4DuE7Z8LIwlxbUYbQ/o.jpg", "https://s3-media4.fl.yelpcdn.com/bphoto/FsN0XmC-EGZ8z4DPN7xYag/o.jpg", "https://s3-media2.fl.yelpcdn.com/bphoto/K79wi9GrYWtDPtNyWnAdmw/o.jpg"], "coordinates": {"latitude": 37.2373886, "longitude": -121.972641}, "location": {"address3": "", "state": "CA", "address1": "233 Blossom Hill Rd", "country": "US", "address2": "", "zip_code": "95032", "city": "Los Gatos"}}