{"image_url": "", "hours": [{"hours_type": "REGULAR", "is_open_now": true, "open": [{"start": "1100", "day": 5, "end": "1700", "is_overnight": false}, {"start": "1100", "day": 6, "end": "1700", "is_overnight": false}]}], "id": "sydney-jet-sydney", "phone": "+61298074333", "term": "attractions", "rating": 3.0, "is_closed": false, "categories": [{"alias": "boating", "title": "Boating"}], "url": "https://www.yelp.com/biz/sydney-jet-sydney?adjust_creative=92p07_JjKyriZTQxAXRiKQ&utm_campaign=yelp_api_v3&utm_medium=api_v3_business_lookup&utm_source=92p07_JjKyriZTQxAXRiKQ", "review_count": 2, "is_claimed": false, "name": "Sydney Jet", "photos": [], "coordinates": {"latitude": -33.8638, "longitude": 151.1946869}, "location": {"address3": "", "address1": "Cockle Bay Whrf", "state": "NSW", "country": "AU", "address2": "", "zip_code": "2000", "city": "Sydney"}}