{"image_url": "https://s3-media3.fl.yelpcdn.com/bphoto/70FOahAHIHT7UmUH6U7GWQ/o.jpg", "hours": [{"hours_type": "REGULAR", "is_open_now": true, "open": [{"start": "1700", "day": 1, "end": "2230", "is_overnight": false}, {"start": "1700", "day": 2, "end": "2230", "is_overnight": false}, {"start": "1700", "day": 3, "end": "2230", "is_overnight": false}, {"start": "1700", "day": 4, "end": "2230", "is_overnight": false}, {"start": "1700", "day": 5, "end": "2230", "is_overnight": false}, {"start": "1700", "day": 6, "end": "2200", "is_overnight": false}]}], "id": "blr-by-shojo-boston-2", "phone": "+16174775828", "term": "restaurants", "rating": 4.0, "price": "$$", "is_closed": false, "categories": [{"alias": "chinese", "title": "Chinese"}], "url": "https://www.yelp.com/biz/blr-by-shojo-boston-2?adjust_creative=92p07_JjKyriZTQxAXRiKQ&utm_campaign=yelp_api_v3&utm_medium=api_v3_business_lookup&utm_source=92p07_JjKyriZTQxAXRiKQ", "review_count": 138, "is_claimed": true, "name": "BLR By Shojo", "photos": ["https://s3-media4.fl.yelpcdn.com/bphoto/70FOahAHIHT7UmUH6U7GWQ/o.jpg", "https://s3-media2.fl.yelpcdn.com/bphoto/1riUzpHeOUhIBp12mAUNEw/o.jpg", "https://s3-media2.fl.yelpcdn.com/bphoto/mkMZogL1McBVGRI4CZ4Mpw/o.jpg"], "coordinates": {"latitude": 42.3508, "longitude": -71.06025}, "location": {"address3": "", "state": "MA", "address1": "13A Hudson St", "country": "US", "address2": "", "zip_code": "02111", "city": "Boston"}}