{"image_url": "https://s3-media4.fl.yelpcdn.com/bphoto/xnQI9L47wgRVc7JdOXnIHg/o.jpg", "hours": [{"hours_type": "REGULAR", "is_open_now": false, "open": [{"start": "1030", "day": 0, "end": "2100", "is_overnight": false}, {"start": "1030", "day": 1, "end": "2100", "is_overnight": false}, {"start": "1030", "day": 2, "end": "2100", "is_overnight": false}, {"start": "1030", "day": 3, "end": "2100", "is_overnight": false}, {"start": "1030", "day": 4, "end": "1600", "is_overnight": false}, {"start": "1200", "day": 6, "end": "2100", "is_overnight": false}]}], "id": "osis-kitchen-las-vegas-3", "phone": "+17028262727", "term": "restaurants", "rating": 4.5, "price": "$$", "is_closed": false, "categories": [{"alias": "mediterranean", "title": "Mediterranean"}, {"alias": "kosher", "title": "Kosher"}], "url": "https://www.yelp.com/biz/osis-kitchen-las-vegas-3?adjust_creative=92p07_JjKyriZTQxAXRiKQ&utm_campaign=yelp_api_v3&utm_medium=api_v3_business_lookup&utm_source=92p07_JjKyriZTQxAXRiKQ", "review_count": 81, "is_claimed": true, "name": "Osi's Kitchen", "photos": ["https://s3-media1.fl.yelpcdn.com/bphoto/xnQI9L47wgRVc7JdOXnIHg/o.jpg", "https://s3-media3.fl.yelpcdn.com/bphoto/ZYi7L3uBxTr_pYqmTAIsPw/o.jpg", "https://s3-media1.fl.yelpcdn.com/bphoto/4Tt56aqjfR-1o9xLrpF9kg/o.jpg"], "coordinates": {"latitude": 36.1449617255872, "longitude": -115.204817982802}, "location": {"address3": "", "state": "NV", "address1": "4604 W Sahara Ave", "country": "US", "address2": "Ste 6", "zip_code": "89102", "city": "Las Vegas"}}