{"image_url": "", "id": "dryden-lodge-auckland", "coordinates": {"latitude": -36.8615494, "longitude": 174.737381}, "phone": "+6493781282", "term": "hotels", "rating": 0.0, "is_closed": false, "categories": [{"alias": "hotels", "title": "Hotels"}], "url": "https://www.yelp.com/biz/dryden-lodge-auckland?adjust_creative=92p07_JjKyriZTQxAXRiKQ&utm_campaign=yelp_api_v3&utm_medium=api_v3_business_lookup&utm_source=92p07_JjKyriZTQxAXRiKQ", "review_count": 0, "is_claimed": false, "name": "Dryden Lodge", "photos": [], "location": {"city": "Auckland", "state": "AUK", "address1": "27-31 Dryden St", "country": "NZ", "address2": null, "zip_code": "1021", "address3": null}}