{"image_url": "", "id": "execustay-by-marriott-auckland", "rating": 0.0, "phone": "", "term": "hotels", "coordinates": {"latitude": -36.8466415, "longitude": 174.7376556}, "is_closed": false, "categories": [{"alias": "hotels", "title": "Hotels"}], "url": "https://www.yelp.com/biz/execustay-by-marriott-auckland?adjust_creative=92p07_JjKyriZTQxAXRiKQ&utm_campaign=yelp_api_v3&utm_medium=api_v3_business_lookup&utm_source=92p07_JjKyriZTQxAXRiKQ", "review_count": 0, "is_claimed": false, "name": "Execustay By Marriott", "photos": [], "location": {"address1": "17 JOHN ST", "city": "Auckland", "state": "AUK", "address3": null, "address2": null, "zip_code": "1011", "country": "NZ"}}