{"image_url": "", "photos": [], "phone": "+448712244007", "term": "attractions", "rating": 4.0, "is_closed": false, "categories": [{"alias": "movietheaters", "title": "Cinema"}], "url": "https://www.yelp.com/biz/odeon-cinema-liverpool-2?adjust_creative=92p07_JjKyriZTQxAXRiKQ&utm_campaign=yelp_api_v3&utm_medium=api_v3_business_lookup&utm_source=92p07_JjKyriZTQxAXRiKQ", "review_count": 3, "is_claimed": false, "name": "Odeon Cinema", "id": "odeon-cinema-liverpool-2", "coordinates": {"latitude": 53.409288, "longitude": -2.9756877}, "location": {"address3": null, "address1": "London Road", "state": "LIV", "country": "GB", "address2": null, "zip_code": "L3 5NF", "city": "Liverpool"}}